blockchainer/__init__.py
blockchainer/blockchain/__init__.py
blockchainer/blockchain/blockchain.py
blockchainer/miner/__init__.py
blockchainer/miner/miner.py
blockchainer/node/__init__.py
blockchainer/script/__init__.py
blockchainer/script/script.py
blockchainer/wallet/__init__.py
blockchainer/wallet/wallet.py
blockchainer-0.0.6.dist-info/LICENSE
blockchainer-0.0.6.dist-info/METADATA
blockchainer-0.0.6.dist-info/WHEEL
blockchainer-0.0.6.dist-info/top_level.txt
blockchainer-0.0.6.dist-info/RECORD
